juml/__init__.py
juml/base.py
juml/device.py
juml/framework.py
juml/test_utils.py
juml/commands/__init__.py
juml/commands/base.py
juml/commands/compare_sweeps.py
juml/commands/compare_sweeps_copy.py
juml/commands/plot_1d_regression.py
juml/commands/plot_confusion_matrix.py
juml/commands/plot_sequential.py
juml/commands/profile.py
juml/commands/sweep.py
juml/commands/sweep2d.py
juml/commands/train.py
juml/datasets/__init__.py
juml/datasets/base.py
juml/datasets/cifar10.py
juml/datasets/fromdict.py
juml/datasets/lineardataset.py
juml/datasets/mnist.py
juml/datasets/randimg.py
juml/datasets/sinmix.py
juml/datasets/split.py
juml/datasets/synthetic.py
juml/loss/__init__.py
juml/loss/asmse.py
juml/loss/base.py
juml/loss/chamfer.py
juml/loss/crossentropy.py
juml/loss/mse.py
juml/models/__init__.py
juml/models/base.py
juml/models/cnn.py
juml/models/embed.py
juml/models/linear.py
juml/models/linearmodel.py
juml/models/mlp.py
juml/models/pool.py
juml/models/rzcnn.py
juml/models/rzmlp.py
juml/models/sequential.py
juml/tools/__init__.py
juml/tools/display.py
juml/tools/experiment.py
juml/tools/plot_type.py
juml/tools/profiler.py
juml/tools/sweeper.py
juml/train/__init__.py
juml/train/base.py
juml/train/bpsp.py
juml/train/bpspde.py
juml_toolkit-0.0.5.dist-info/licenses/LICENSE
juml_toolkit-0.0.5.dist-info/METADATA
juml_toolkit-0.0.5.dist-info/WHEEL
juml_toolkit-0.0.5.dist-info/entry_points.txt
juml_toolkit-0.0.5.dist-info/top_level.txt
juml_toolkit-0.0.5.dist-info/RECORD
