Metadata-Version: 2.4
Name: juml-toolkit
Version: 0.0.5
Summary: A Judicious, Unified and extendable framework for multi-paradigm Machine Learning research, powered by jutility and PyTorch.
Author: Jake Levi
Author-email: jakelevi@hotmail.co.uk
License: MIT License
Project-URL: Homepage, https://github.com/jakelevi1996/juml/
Project-URL: Documentation, https://github.com/jakelevi1996/juml/
Project-URL: Repository, https://github.com/jakelevi1996/juml/
Requires-Python: >=3.10
License-File: LICENSE
Requires-Dist: jutility>=0.0.23
Dynamic: license-file
